ctgu_demo1/__init__.py
ctgu_demo1-0.1.0.dist-info/WHEEL
ctgu_demo1-0.1.0.dist-info/entry_points.txt
ctgu_demo1-0.1.0.dist-info/METADATA
ctgu_demo1-0.1.0.dist-info/RECORD
