Metadata-Version: 2.3
Name: ctgu-demo1
Version: 0.1.0
Summary: Add your description here
Author: 郭晓阳
Author-email: 郭晓阳 <guoxiaoyang@ctgu.edu.cn>
Requires-Dist: mcp[cli]>=1.25.0
Requires-Python: >=3.13
